aria/__init__.py
aria/field.py
aria/form.py
aria/walker.py
aria-0.4.5.dist-info/LICENSE
aria-0.4.5.dist-info/METADATA
aria-0.4.5.dist-info/WHEEL
aria-0.4.5.dist-info/top_level.txt
aria-0.4.5.dist-info/RECORD
